cert_blitz/__init__.py
cert_blitz/main.py
cert_blitz/prompts.py
cert_blitz-2025.12.22080137.dist-info/METADATA
cert_blitz-2025.12.22080137.dist-info/WHEEL
cert_blitz-2025.12.22080137.dist-info/top_level.txt
cert_blitz-2025.12.22080137.dist-info/RECORD
