Metadata-Version: 2.4
Name: cert-blitz
Version: 2025.12.22080137
Summary: decodes and analyzes digital certificates and TLS server configurations from text input.
Author-email: cert-blitz <hi@eugene.plus>
License: MIT
Project-URL: Homepage, https://github.com/chigwell/cert-blitz
Requires-Python: >=3.9
Requires-Dist: langchain-llm7>=0.0.0
Requires-Dist: llmatch-messages>=0.0.0
Requires-Dist: langchain-core>=0.3.0
